Adafruit_MCP9808-1.5.3.dist-info/metadata.json
Adafruit_MCP9808-1.5.3.dist-info/METADATA
Adafruit_MCP9808-1.5.3.dist-info/RECORD
Adafruit_MCP9808-1.5.3.dist-info/WHEEL
Adafruit_MCP9808-1.5.3.dist-info/DESCRIPTION.rst
Adafruit_MCP9808-1.5.3.dist-info/dependency_links.txt
Adafruit_MCP9808-1.5.3.dist-info/top_level.txt
Adafruit_MCP9808/MCP9808.py
Adafruit_MCP9808/__init__.py
