Metadata-Version: 2.0
Name: Adafruit-MCP9808
Version: 1.5.3
Summary: Library for accessing the MCP9808 precision temperature sensor on a Raspberry Pi or Beaglebone Black.
Home-page: https://github.com/adafruit/Adafruit_Python_MCP9808/
Author: Tony DiCola
Author-email: tdicola@adafruit.com
License: MIT
Platform: UNKNOWN
Classifier: Development Status :: 4 - Beta
Classifier: Operating System :: POSIX :: Linux
Classifier: License :: OSI Approved :: MIT License
Classifier: Intended Audience :: Developers
Classifier: Programming Language :: Python :: 2.7
Classifier: Programming Language :: Python :: 3
Classifier: Topic :: Software Development
Classifier: Topic :: System :: Hardware
Requires-Dist: Adafruit-GPIO (>=0.6.5)
